qtcurate/__init__.py
qtcurate/__version__.py
qtcurate/config.py
qtcurate/connect.py
qtcurate/document.py
qtcurate/exceptions.py
qtcurate/extractor.py
qtcurate/job.py
qtcurate/model.py
qtcurate/qt.py
qtcurate/result.py
qtcurate/vocabulary.py
qtcurate-2.2.7.dist-info/LICENSE
qtcurate-2.2.7.dist-info/METADATA
qtcurate-2.2.7.dist-info/WHEEL
qtcurate-2.2.7.dist-info/top_level.txt
qtcurate-2.2.7.dist-info/RECORD
