Metadata-Version: 2.1
Name: qtcurate
Version: 2.2.7
Summary: Theia SDK Search and Data Extraction
Home-page: https://github.com/quantxt/qtcurate-sdk-python
Author: Milojko Bjelanovic
Author-email: mbjelanovic@quantxt.com
License: Apache License 2.0
Platform: UNKNOWN
Classifier: License :: OSI Approved :: Apache Software License
Classifier: Programming Language :: Python :: 3
Classifier: Programming Language :: Python :: 3.6
Classifier: Programming Language :: Python :: 3.7
Classifier: Programming Language :: Python :: 3.8
Classifier: Programming Language :: Python :: 3.9
Requires-Python: >=3.6
Requires-Dist: requests
Requires-Dist: smart-open
